{"version_id": "0.560", "interface_hash": "b4650713a70873be34154a674d150fd6", "id": "typing", "size": 18819, "mtime": 1514389922, "data_mtime": 1523566403, "ignore_all": false, "child_modules": [], "dependencies": ["sys", "abc", "types", "collections", "builtins"], "hash": "7fb90623e71190f1a3e923529f493a51", "options": {"disallow_any_generics": false, "disallow_subclassing_any": false, "disallow_untyped_defs": false, "platform": "linux", "ignore_errors": false, "ignore_missing_imports": false, "check_untyped_defs": false, "disallow_any_decorated": false, "disallow_untyped_decorators": false, "quick_and_dirty": false, "strict_boolean": false, "show_none_errors": true, "warn_no_return": true, "no_implicit_optional": false, "strict_optional_whitelist": null, "disallow_untyped_calls": false, "warn_return_any": false, "disallow_any_expr": false, "disallow_any_unimported": false, "disallow_any_explicit": false, "strict_optional": false, "follow_imports": "normal"}, "dep_prios": [10, 5, 5, 10, 5], "path": "/usr/local/lib/mypy/typeshed/stdlib/3/typing.pyi", "suppressed": []}
